{"B":{"d":{"r":"\u2554","h":"\u2566","l":"\u2557"},"u":{"r":"\u255a","h":"\u2569","l":"\u255d"},"v":{"r":"\u2560","h":"\u256c","l":"\u2563"}},"D":{"h":"\u2530","r":{"u":"\u251f","none":"\u250e"},"u":{"h":"\u2541"},"H":"\u2533","l":{"u":"\u2527","none":"\u2512"},"none":"\u257b","L":"\u2513","R":"\u250f"},"H":"\u2501","L":{"r":{"d":"\u252d","u":"\u2535","v":"\u253d","none":"\u257e"},"D":{"r":{"u":"\u2545"}},"U":{"r":{"d":"\u2543"}},"none":"\u2578"},"R":{"D":{"l":{"u":"\u2546"}},"U":{"l":{"d":"\u2544"}},"none":"\u257a","l":{"d":"\u252e","u":"\u2536","v":"\u253e"}},"U":{"h":"\u2538","r":{"d":"\u251e","none":"\u2516"},"d":{"h":"\u2540","none":"\u257f"},"H":"\u253b","l":{"d":"\u2526","none":"\u251a"},"none":"\u2579","L":"\u251b","R":"\u2517"},"V":{"none":"\u2503","r":"\u2520","h":"\u2542","l":"\u2528","L":"\u252b","R":"\u2523","H":"\u254b"},"\\":"\u2572","a":{"d":{"r":"\u256d","l":"\u256e"},"u":{"r":"\u2570","l":"\u256f"}},"b":{"d":{"r":"\u2553","h":"\u2565","l":"\u2556"},"u":{"r":"\u2559","h":"\u2568","l":"\u255c"},"v":{"none":"\u2551","r":"\u255f","h":"\u256b","l":"\u2562"},"h":"\u2550"},"d":{"none":"\u2577","r":"\u250c","R":{"U":"\u2521","none":"\u250d"},"U":{"H":"\u2547"},"l":"\u2510","H":"\u252f","h":"\u252c","L":{"U":"\u2529","none":"\u2511"},"b":{"r":"\u2552","h":"\u2564","l":"\u2555"}},"h":"\u2500","l":{"R":{"D":"\u2532","U":"\u253a","V":"\u254a","none":"\u257c"},"none":"\u2574"},"2":{"h":"\u254c","v":"\u254e","V":"\u254f","H":"\u254d"},"\/":"\u2571","r":{"none":"\u2576","L":{"D":"\u2531","U":"\u2539","V":"\u2549"}},"3":{"h":"\u2504","v":"\u2506","V":"\u2507","H":"\u2505"},"4":{"h":"\u2508","v":"\u250a","V":"\u250b","H":"\u2509"},"u":{"h":"\u2534","r":"\u2514","D":{"H":"\u2548","none":"\u257d"},"R":{"D":"\u2522","none":"\u2515"},"H":"\u2537","l":"\u2518","none":"\u2575","L":{"D":"\u252a","none":"\u2519"},"b":{"r":"\u2558","h":"\u2567","l":"\u255b"}},"v":{"none":"\u2502","r":"\u251c","R":"\u251d","h":"\u253c","l":"\u2524","L":"\u2525","b":{"r":"\u255e","h":"\u256a","l":"\u2561"},"H":"\u253f"},"x":"\u2573"}
